stabilofont/__init__.py
stabilofont-0.3.dist-info/LICENCE
stabilofont-0.3.dist-info/METADATA
stabilofont-0.3.dist-info/WHEEL
stabilofont-0.3.dist-info/top_level.txt
stabilofont-0.3.dist-info/RECORD
