Metadata-Version: 2.1
Name: stabilofont
Version: 0.3
Summary: stabilofont is a package for change text color in terminal/cmd when you print some important text
Home-page: https://github.com/rizki4106/stabilo
Author: Rizki Maulana
Author-email: rizkimaulana348@gmail.com
License: MIT
Download-URL: https://github.com/rizki4106/stabilo/archive/master.zip
Keywords: colors,color,font,background,style
Platform: UNKNOWN
Classifier: License :: OSI Approved :: MIT License
Classifier: Programming Language :: Python :: 3
Classifier: Programming Language :: Python :: 3.7
